[
    {
        "ID": "312",
        "name": "                Colloidal Minerals with Asai — Колло...      ",
        "url": "https://lovemylife.nsp25.md/product/colloidal-minerals-with-asai-kolloidnye-mineraly-s-sokom-asai",
        "img_url": "https://lovemylife.nsp25.md/wp-content/uploads/2021/04/colloidal_minerals_with_acai_juice_1-150x150.jpg",
        "price": "30,59 $"
    },
    {
        "ID": "6274",
        "name": "                Colloidal Silver Forte — Коллоидное ...      ",
        "url": "https://lovemylife.nsp25.md/product/colloidal-silver-forte-kolloidnoe-serebro-forte",
        "img_url": "https://lovemylife.nsp25.md/wp-content/uploads/2021/04/colloidal_silver_20ppm_1_-150x150.jpg",
        "price": "36,04 $"
    },
    {
        "ID": "1828",
        "name": "                Colostrum — Колострум      ",
        "url": "https://lovemylife.nsp25.md/product/colostrum-kolostrum",
        "img_url": "https://lovemylife.nsp25.md/wp-content/uploads/2021/04/142626_1-150x150.jpg",
        "price": "20,45 $"
    },
    {
        "ID": "62203",
        "name": "                Compact Powder «Biscuit» — Компактна...      ",
        "url": "https://lovemylife.nsp25.md/product/compact-powder-biscuit-kompaktnaja-pudra-biskvit",
        "img_url": "https://lovemylife.nsp25.md/wp-content/uploads/2021/04/62203-150x150.png",
        "price": "19,47 $"
    },
    {
        "ID": "61567",
        "name": "                Cool Comfort — Гель После Бритья      ",
        "url": "https://lovemylife.nsp25.md/product/cool-comfort-gel-posle-britja",
        "img_url": "https://lovemylife.nsp25.md/wp-content/uploads/2021/04/file_2-150x150.png",
        "price": "11,32 $"
    },
    {
        "ID": "1873",
        "name": "                Coral Calcium — Коралловый Кальций      ",
        "url": "https://lovemylife.nsp25.md/product/coral-calcium-korallovyj-kalcij",
        "img_url": "https://lovemylife.nsp25.md/wp-content/uploads/2021/04/142625_1-150x150.jpg",
        "price": "39,49 $"
    },
    {
        "ID": "1240",
        "name": "                Cordyceps — Кордицепс      ",
        "url": "https://lovemylife.nsp25.md/product/cordyceps-kordiceps",
        "img_url": "https://lovemylife.nsp25.md/wp-content/uploads/2021/04/142624_4-1-150x150.jpg",
        "price": "41,76 $"
    },
    {
        "ID": "21601",
        "name": "                Day Anti-age Face Cream — Дневной ан...      ",
        "url": "https://lovemylife.nsp25.md/product/day-anti-age-face-cream-dnevnoj-antivozrastnoj-krem-dlja-lica-spf15-40",
        "img_url": "https://lovemylife.nsp25.md/wp-content/uploads/2021/04/21601_1__1-150x150.jpg",
        "price": "33,37 $"
    },
    {
        "ID": "1654",
        "name": "                Defense Maintenance — Защитная Формула      ",
        "url": "https://lovemylife.nsp25.md/product/defense-maintenance-zashhitnaja-formula",
        "img_url": "https://lovemylife.nsp25.md/wp-content/uploads/2021/04/142622_4-1-150x150.jpg",
        "price": "34,45 $"
    },
    {
        "ID": "1360",
        "name": "                E-Tea — Е-Чай      ",
        "url": "https://lovemylife.nsp25.md/product/e-tea-e-chaj",
        "img_url": "https://lovemylife.nsp25.md/wp-content/uploads/2021/04/142619_1_7_1_1-150x150.jpg",
        "price": "21,86 $"
    },
    {
        "ID": "262",
        "name": "                Echinacea — Эхинацея      ",
        "url": "https://lovemylife.nsp25.md/product/echinacea-jehinaceja",
        "img_url": "https://lovemylife.nsp25.md/wp-content/uploads/2021/04/echinacea-nsp-ehkhinaceya-preparat-bad-pishche-kapsuly-otzyvy-cena-instrukciya-primeneniya-kupit-v-ukraine-kiev-harkov-odessa-dnepr-zaporozhe-nikolaev-600x600-1-150x150.jpg",
        "price": "13,99 $"
    },
    {
        "ID": "850",
        "name": "                Eight — Восьмерка      ",
        "url": "https://lovemylife.nsp25.md/product/eight-vosmerka",
        "img_url": "https://lovemylife.nsp25.md/wp-content/uploads/2021/04/142620_1-150x150.jpg",
        "price": "18,30 $"
    }
]